MANIFEST.in
setup.py
opal_pathway.egg-info/PKG-INFO
opal_pathway.egg-info/SOURCES.txt
opal_pathway.egg-info/dependency_links.txt
opal_pathway.egg-info/top_level.txt
pathway/__init__.py
pathway/api.py
pathway/models.py
pathway/pathways.py
pathway/plugin.py
pathway/steps.py
pathway/urls.py
pathway/views.py
pathway/static/js/pathway/app.js
pathway/static/js/pathway/directives.js
pathway/static/js/pathway/controllers/default_single_step.js
pathway/static/js/pathway/controllers/default_step.js
pathway/static/js/pathway/controllers/find_patient.js
pathway/static/js/pathway/controllers/modal_pathway_ctrl.js
pathway/static/js/pathway/controllers/pathway_ctrl.js
pathway/static/js/pathway/controllers/pathway_redirect.js
pathway/static/js/pathway/services/pathway.js
pathway/static/js/pathway/services/pathway_loader.js
pathway/static/js/pathway/services/wizard_pathway.js
pathway/static/js/pathwaytest/app.test.js
pathway/static/js/pathwaytest/default_single_step.service.test.js
pathway/static/js/pathwaytest/directives.test.js
pathway/static/js/pathwaytest/find_patient.controller.test.js
pathway/static/js/pathwaytest/modal_pathway.controller.test.js
pathway/static/js/pathwaytest/pathway.controller.test.js
pathway/static/js/pathwaytest/pathway.service.test.js
pathway/static/js/pathwaytest/pathway_loader.service.test.js
pathway/static/js/pathwaytest/pathway_redirect.controller.test.js
pathway/static/js/pathwaytest/pathway_wizard.service.test.js
pathway/templates/.DS_Store
pathway/templates/_helpers/multisave.html
pathway/templates/pathway/.DS_Store
pathway/templates/pathway/find_patient_form.html
pathway/templates/pathway/index.html
pathway/templates/pathway/partial/cancel_button.html
pathway/templates/pathway/partial/save_button.html
pathway/templates/pathway/partial/wizard_back_button.html
pathway/templates/pathway/partial/wizard_next_button.html
pathway/templates/pathway/partial/wizard_pathway_body.html
pathway/templates/pathway/pathway_bases/.DS_Store
pathway/templates/pathway/steps/multi_save.html
pathway/templates/pathway/templates/modal_no_footer.html
pathway/templates/pathway/templates/modal_page_pathway.html
