Metadata-Version: 1.0
Name: opal-pathway
Version: 0.4
Summary: The pathway OPAL Plugin
Home-page: http://opal.openhealthcare.org.uk/
Author: UNKNOWN
Author-email: UNKNOWN
License: LICENSE
Platform: UNKNOWN
